Workbook

Sheet 案件管理
A1: 案件No | B1: 受付日 | C1: 受付時刻 | D1: 問合せ経路 | E1: 広告経由 | F1: 検索KW | G1: お客様名 | H1: 電話番号 | I1: 住所 | J1: 建物種別 | K1: 築年数 | L1: 症状概要 | M1: 訪問希望日 | N1: 訪問確定日 | O1: 訪問時刻 | P1: 担当者 | Q1: 現地所見 | R1: 作業内容 | S1: 作業時間(分) | T1: 見積額 | U1: 成約 | V1: 辞退理由 | W1: 実受領額 | X1: 材料費 | Y1: 粗利 | Z1: 支払方法 | AA1: 完了日 | AB1: 保証期限 | AC1: アフター | AD1: 口コミ依頼 | AE1: クレーム | AF1: 備考
A2: 001 | B2: 2026-04-15 | C2: 10:30 | D2: 電話 | E2: YES | F2: 排水 詰まり 名古屋 | G2: 山田 太郎 | H2: 090-1234-5678 | I2: 名古屋市中川区○○町1-2-3 | J2: 戸建て | K2: 25 | L2: キッチン排水が流れない。ゴボゴボ音あり | M2: 2026-04-15 | N2: 2026-04-15 | O2: 14:00 | P2: 土屋 | Q2: 排水管の油脂蓄積。屋外升も汚泥多め | R2: キッチン排水管 高圧洗浄 + 屋外升清掃 | S2: 90 | T2: 33000 | U2: YES | W2: 33000 | X2: 2500 | Y2: =IF(W2="","",W2-X2) | Z2: 現金 | AA2: 2026-04-15 | AB2: =IF(AA2="","",AA2+30) | AC2: YES | AD2: NO | AE2: NO | AF2: 口コミ投稿依頼済（LINEで依頼）
Y3: =IF(W3="","",W3-X3) | AB3: =IF(AA3="","",AA3+30)
Y4: =IF(W4="","",W4-X4) | AB4: =IF(AA4="","",AA4+30)
Y5: =IF(W5="","",W5-X5) | AB5: =IF(AA5="","",AA5+30)
Y6: =IF(W6="","",W6-X6) | AB6: =IF(AA6="","",AA6+30)
Y7: =IF(W7="","",W7-X7) | AB7: =IF(AA7="","",AA7+30)
Y8: =IF(W8="","",W8-X8) | AB8: =IF(AA8="","",AA8+30)
Y9: =IF(W9="","",W9-X9) | AB9: =IF(AA9="","",AA9+30)
Y10: =IF(W10="","",W10-X10) | AB10: =IF(AA10="","",AA10+30)
Y11: =IF(W11="","",W11-X11) | AB11: =IF(AA11="","",AA11+30)
Y12: =IF(W12="","",W12-X12) | AB12: =IF(AA12="","",AA12+30)
Y13: =IF(W13="","",W13-X13) | AB13: =IF(AA13="","",AA13+30)
Y14: =IF(W14="","",W14-X14) | AB14: =IF(AA14="","",AA14+30)
... Y51: =IF(W51="","",W51-X51) | AB51: =IF(AA51="","",AA51+30)

Sheet ダッシュボード
B2: 匠 - 経営ダッシュボード
B4: 問合せ・成約 | F4: 売上・粗利
B5: 今月の受付件数 | C5: =COUNTA(案件管理!B2:B200)-COUNTIF(案件管理!B2:B200,"<>"&"")+COUNTIFS(案件管理!B2:B200,">="&EOMONTH(TODAY(),-1)+1,案件管理!B2:B200,"<="&EOMONTH(TODAY(),0)) | D5: 件 | F5: 今月売上 | G5: =SUMIFS(案件管理!W2:W200,案件管理!B2:B200,">="&EOMONTH(TODAY(),-1)+1,案件管理!B2:B200,"<="&EOMONTH(TODAY(),0))
B6: 今月の成約件数 | C6: =COUNTIFS(案件管理!B2:B200,">="&EOMONTH(TODAY(),-1)+1,案件管理!B2:B200,"<="&EOMONTH(TODAY(),0),案件管理!U2:U200,"YES") | D6: 件 | F6: 今月粗利 | G6: =SUMIFS(案件管理!Y2:Y200,案件管理!B2:B200,">="&EOMONTH(TODAY(),-1)+1,案件管理!B2:B200,"<="&EOMONTH(TODAY(),0))
B7: 成約率 | C7: =IFERROR(COUNTIFS(案件管理!B2:B200,">="&EOMONTH(TODAY(),-1)+1,案件管理!B2:B200,"<="&EOMONTH(TODAY(),0),案件管理!U2:U200,"YES")/COUNTIFS(案件管理!B2:B200,">="&EOMONTH(TODAY(),-1)+1,案件管理!B2:B200,"<="&EOMONTH(TODAY(),0)),"") | D7: % | F7: 平均客単価 | G7: =IFERROR(AVERAGEIFS(案件管理!W2:W200,案件管理!B2:B200,">="&EOMONTH(TODAY(),-1)+1,案件管理!B2:B200,"<="&EOMONTH(TODAY(),0),案件管理!U2:U200,"YES"),"")
B8: 電話経由 比率 | C8: =IFERROR(COUNTIFS(案件管理!B2:B200,">="&EOMONTH(TODAY(),-1)+1,案件管理!B2:B200,"<="&EOMONTH(TODAY(),0),案件管理!D2:D200,"電話")/COUNTIFS(案件管理!B2:B200,">="&EOMONTH(TODAY(),-1)+1,案件管理!B2:B200,"<="&EOMONTH(TODAY(),0)),"") | D8: % | F8: 平均粗利 | G8: =IFERROR(AVERAGEIFS(案件管理!Y2:Y200,案件管理!B2:B200,">="&EOMONTH(TODAY(),-1)+1,案件管理!B2:B200,"<="&EOMONTH(TODAY(),0),案件管理!U2:U200,"YES"),"")
B9: LINE経由 比率 | C9: =IFERROR(COUNTIFS(案件管理!B2:B200,">="&EOMONTH(TODAY(),-1)+1,案件管理!B2:B200,"<="&EOMONTH(TODAY(),0),案件管理!D2:D200,"LINE")/COUNTIFS(案件管理!B2:B200,">="&EOMONTH(TODAY(),-1)+1,案件管理!B2:B200,"<="&EOMONTH(TODAY(),0)),"") | D9: % | F9: 粗利率 | G9: =IFERROR(SUMIFS(案件管理!Y2:Y200,案件管理!B2:B200,">="&EOMONTH(TODAY(),-1)+1,案件管理!B2:B200,"<="&EOMONTH(TODAY(),0))/SUMIFS(案件管理!W2:W200,案件管理!B2:B200,">="&EOMONTH(TODAY(),-1)+1,案件管理!B2:B200,"<="&EOMONTH(TODAY(),0)),"")
B12: 要フォロー
B13: クレーム件数（今月） | G13: =COUNTIFS(案件管理!B2:B200,">="&EOMONTH(TODAY(),-1)+1,案件管理!B2:B200,"<="&EOMONTH(TODAY(),0),案件管理!AE2:AE200,"YES")
B14: アフター未対応 | G14: =COUNTIFS(案件管理!U2:U200,"YES",案件管理!AC2:AC200,"NO")
B15: 保証期間内の案件数 | G15: =COUNTIFS(案件管理!AB2:AB200,">="&TODAY())
B16: 口コミ依頼未実施 | G16: =COUNTIFS(案件管理!U2:U200,"YES",案件管理!AD2:AD200,"NO")
B18: ※ データは「案件管理」シートに入力するとここに自動集計されます。 ※ 「受付日」を入れると当月集計に反映されます。 ※ KPI詳細分析は「月次収支表.xlsx」と併せてご確認ください。
